<?xml version="1.0" encoding="utf-8" ?>
<odoo>
    <record id="action_sign_logs_hpp" model="ir.actions.server">
        <field name="name">Sign logs</field>
        <field name="model_id" ref="model_hpp_log" />
        <field name="binding_model_id" ref="model_hpp_log" />
        <field name="state">code</field>
        <field name="binding_view_types">list</field>
        <field name="code">
            for record in records:
            record.action_sign_log()
        </field>
    </record>

    <record id="action_sign_logs_coding" model="ir.actions.server">
        <field name="name">Sign logs</field>
        <field name="model_id" ref="model_coding_log" />
        <field name="binding_model_id" ref="model_coding_log" />
        <field name="state">code</field>
        <field name="binding_view_types">list</field>
        <field name="code">
            for record in records:
            record.action_sign_log()
        </field>
    </record>
    <record id="action_sign_logs_metal" model="ir.actions.server">
        <field name="name">Sign logs</field>
        <field name="model_id" ref="model_metal_log" />
        <field name="binding_model_id" ref="model_metal_log" />
        <field name="state">code</field>
        <field name="binding_view_types">list</field>
        <field name="code">
            for record in records:
            record.action_sign_log()
        </field>
    </record>
    <record id="action_sign_logs_loma" model="ir.actions.server">
        <field name="name">Sign logs</field>
        <field name="model_id" ref="model_loma_log" />
        <field name="binding_model_id" ref="model_loma_log" />
        <field name="state">code</field>
        <field name="binding_view_types">list</field>
        <field name="code">
            for record in records:
            record.action_sign_log()
        </field>
    </record>
    <record id="action_sign_logs_x_ray" model="ir.actions.server">
        <field name="name">Sign logs</field>
        <field name="model_id" ref="model_x_ray_log" />
        <field name="binding_model_id" ref="model_x_ray_log" />
        <field name="state">code</field>
        <field name="binding_view_types">list</field>
        <field name="code">
            for record in records:
            record.action_sign_log()
        </field>
    </record>
</odoo>
